search/__init__.py
search/main.py
clisearch-0.1.dist-info/METADATA
clisearch-0.1.dist-info/WHEEL
clisearch-0.1.dist-info/entry_points.txt
clisearch-0.1.dist-info/top_level.txt
clisearch-0.1.dist-info/RECORD
